.gitignore
LICENSE
MANIFEST.in
README.md
README.rst
requirements.txt
setup.cfg
setup.py
flask_editormd/__init__.py
flask_editormd/fields.py
flask_editormd/widgets.py
flask_editormd.egg-info/PKG-INFO
flask_editormd.egg-info/SOURCES.txt
flask_editormd.egg-info/dependency_links.txt
flask_editormd.egg-info/requires.txt
flask_editormd.egg-info/top_level.txt
flask_editormd/static/css/editormd.min.css
flask_editormd/static/css/editormd.preview.min.css
flask_editormd/static/fonts/FontAwesome.otf
flask_editormd/static/fonts/editormd-logo.eot
flask_editormd/static/fonts/editormd-logo.svg
flask_editormd/static/fonts/editormd-logo.ttf
flask_editormd/static/fonts/editormd-logo.woff
flask_editormd/static/fonts/fontawesome-webfont.eot
flask_editormd/static/fonts/fontawesome-webfont.svg
flask_editormd/static/fonts/fontawesome-webfont.ttf
flask_editormd/static/fonts/fontawesome-webfont.woff
flask_editormd/static/fonts/fontawesome-webfont.woff2
flask_editormd/static/images/loading.gif
flask_editormd/static/images/loading@2x.gif
flask_editormd/static/images/loading@3x.gif
flask_editormd/static/images/logos/editormd-favicon-16x16.ico
flask_editormd/static/images/logos/editormd-favicon-24x24.ico
flask_editormd/static/images/logos/editormd-favicon-32x32.ico
flask_editormd/static/images/logos/editormd-favicon-48x48.ico
flask_editormd/static/images/logos/editormd-favicon-64x64.ico
flask_editormd/static/images/logos/editormd-logo-114x114.png
flask_editormd/static/images/logos/editormd-logo-120x120.png
flask_editormd/static/images/logos/editormd-logo-144x144.png
flask_editormd/static/images/logos/editormd-logo-16x16.png
flask_editormd/static/images/logos/editormd-logo-180x180.png
flask_editormd/static/images/logos/editormd-logo-240x240.png
flask_editormd/static/images/logos/editormd-logo-24x24.png
flask_editormd/static/images/logos/editormd-logo-320x320.png
flask_editormd/static/images/logos/editormd-logo-32x32.png
flask_editormd/static/images/logos/editormd-logo-48x48.png
flask_editormd/static/images/logos/editormd-logo-57x57.png
flask_editormd/static/images/logos/editormd-logo-64x64.png
flask_editormd/static/images/logos/editormd-logo-72x72.png
