Metadata-Version: 1.2
Name: flask-editormd
Version: 0.0.7
Summary: Implementation of editor.md the markdown editor for Flask and Flask-WTF.
Home-page: https://github.com/a358003542/flask-editormd
Author: wanze
Author-email: a358003542@gmail.com
Maintainer: wanze
Maintainer-email: a358003542@gmail.com
License: MIT
Keywords: flask
Platform: Linux
Classifier: Development Status :: 4 - Beta
Classifier: Environment :: Console
Classifier: Operating System :: Microsoft :: Windows
Classifier: Operating System :: POSIX :: Linux
Classifier: License :: OSI Approved :: MIT License
Classifier: Framework :: Flask
Classifier: Programming Language :: Python :: 3.4
Classifier: Programming Language :: Python :: 3.5
Classifier: Programming Language :: Python :: 3.6
